pytyped/macros/__init__.py
pytyped/macros/boxed.py
pytyped/macros/extractor.py
pytyped/macros/py.typed
pytyped/macros/pyjack.py
pytyped_macros-1.0.1.dist-info/LICENSE
pytyped_macros-1.0.1.dist-info/METADATA
pytyped_macros-1.0.1.dist-info/WHEEL
pytyped_macros-1.0.1.dist-info/top_level.txt
pytyped_macros-1.0.1.dist-info/RECORD
