Metadata-Version: 2.1
Name: pytyped-macros
Version: 1.0.1
Summary: Type-Driven Development for Python: Shapes of Types
Home-page: https://github.com/stasharrofi/pytyped/tree/master/pytyped-macros
Author: Shahab Tasharrofi
Author-email: shahab.tasharrofi@gmail.com
License: UNKNOWN
Platform: UNKNOWN
Classifier: Programming Language :: Python :: 3
Classifier: License :: OSI Approved :: MIT License
Classifier: Operating System :: OS Independent
Requires-Python: >=3.6
License-File: LICENSE
